leesah/__init__.py
leesah/kafka_config.py
leesah/kviss_rapid.py
leesah/modeller.py
leesah/quiz_rapid.py
leesah_game-1.4.1.dist-info/licenses/LICENSE
leesah_game-1.4.1.dist-info/METADATA
leesah_game-1.4.1.dist-info/WHEEL
leesah_game-1.4.1.dist-info/top_level.txt
leesah_game-1.4.1.dist-info/RECORD
