Metadata-Version: 2.4
Name: leesah-game
Version: 1.4.1
Summary: Leesah er et Pythonbibliotek for å spille det hendelsedrevet applikasjonsutviklingspillet Leesah Game
Author-email: Nav <kyrre.havik@nav.no>
License-Expression: MIT
Project-URL: Homepage, https://leesah.io
Project-URL: Repository, https://github.com/navikt/leesah-game-python.git
Requires-Python: >=3.9
License-File: LICENSE
Requires-Dist: confluent-kafka>=2.10.0
Requires-Dist: pydantic>=2.11.4
Requires-Dist: pyyaml>=6.0.2
Dynamic: license-file
